cs/translator/elhuyar/__init__.py
cs/translator/elhuyar/configure.zcml
cs/translator/elhuyar/interfaces.py
cs/translator/elhuyar/permissions.zcml
cs/translator/elhuyar/setuphandlers.py
cs/translator/elhuyar/testing.py
cs/translator/elhuyar/api/__init__.py
cs/translator/elhuyar/api/configure.zcml
cs/translator/elhuyar/api/translator/configure.zcml
cs/translator/elhuyar/api/translator/post.py
cs/translator/elhuyar/browser/__init__.py
cs/translator/elhuyar/browser/configure.zcml
cs/translator/elhuyar/browser/static/.gitkeep
cs/translator/elhuyar/browser/static/elhuyar.css
cs/translator/elhuyar/browser/static/elhuyar.js
cs/translator/elhuyar/browser/static/elia_RGB.webp
cs/translator/elhuyar/controlpanels/__init__.py
cs/translator/elhuyar/controlpanels/configure.zcml
cs/translator/elhuyar/controlpanels/elhuyar_a_p_i_config/__init__.py
cs/translator/elhuyar/controlpanels/elhuyar_a_p_i_config/configure.zcml
cs/translator/elhuyar/controlpanels/elhuyar_a_p_i_config/controlpanel.py
cs/translator/elhuyar/locales/README.rst
cs/translator/elhuyar/locales/__init__.py
cs/translator/elhuyar/locales/__main__.py
cs/translator/elhuyar/locales/cs.translator.elhuyar.pot
cs/translator/elhuyar/locales/en/LC_MESSAGES/cs.translator.elhuyar.po
cs/translator/elhuyar/profiles/default/browserlayer.xml
cs/translator/elhuyar/profiles/default/catalog.xml
cs/translator/elhuyar/profiles/default/controlpanel.xml
cs/translator/elhuyar/profiles/default/metadata.xml
cs/translator/elhuyar/profiles/default/rolemap.xml
cs/translator/elhuyar/profiles/default/registry/bundles.xml
cs/translator/elhuyar/profiles/default/registry/elhuyar_a_p_i_config.xml
cs/translator/elhuyar/profiles/default/registry/main.xml
cs/translator/elhuyar/profiles/uninstall/browserlayer.xml
cs/translator/elhuyar/profiles/uninstall/controlpanel.xml
cs/translator/elhuyar/profiles/uninstall/registry/bundles.xml
cs/translator/elhuyar/profiles/uninstall/registry/elhuyar_a_p_i_config.xml
cs/translator/elhuyar/tests/__init__.py
cs_translator_elhuyar-2.0.3.dist-info/licenses/LICENSE.GPL
cs_translator_elhuyar-2.0.3.dist-info/licenses/LICENSE.rst
cs_translator_elhuyar-2.0.3.dist-info/METADATA
cs_translator_elhuyar-2.0.3.dist-info/WHEEL
cs_translator_elhuyar-2.0.3.dist-info/entry_points.txt
cs_translator_elhuyar-2.0.3.dist-info/top_level.txt
cs_translator_elhuyar-2.0.3.dist-info/RECORD
