Metadata-Version: 2.4
Name: cs.translator.elhuyar
Version: 2.0.3
Summary: An add-on for Plone
Home-page: https://github.com/codesyntax/cs.translator.elhuyar
Author: Ion Lizarazu
Author-email: ilizarazu@codesyntax.com
License: GPL version 2
Project-URL: PyPI, https://pypi.org/project/cs.translator.elhuyar/
Project-URL: Source, https://github.com/codesyntax/cs.translator.elhuyar
Project-URL: Tracker, https://github.com/codesyntax/cs.translator.elhuyar/issues
Keywords: Python Plone CMS
Classifier: Development Status :: 5 - Production/Stable
Classifier: Environment :: Web Environment
Classifier: Framework :: Plone
Classifier: Framework :: Plone :: 6.0
Classifier: Framework :: Plone :: 6.1
Classifier: Framework :: Plone :: 6.2
Classifier: Framework :: Plone :: Addon
Classifier: Programming Language :: Python
Classifier: Programming Language :: Python :: 3.10
Classifier: Programming Language :: Python :: 3.11
Classifier: Programming Language :: Python :: 3.12
Classifier: Programming Language :: Python :: 3.13
Classifier: Operating System :: OS Independent
Classifier: License :: OSI Approved :: GNU General Public License v2 (GPLv2)
Requires-Python: >=3.10,<3.14
License-File: LICENSE.GPL
License-File: LICENSE.rst
Requires-Dist: plone.api>=1.8.4
Requires-Dist: plone.restapi
Requires-Dist: requests
Requires-Dist: Products.CMFPlone
Requires-Dist: Zope
Requires-Dist: plone.app.layout
Requires-Dist: plone.app.registry
Requires-Dist: plone.memoize
Requires-Dist: plone.z3cform
Requires-Dist: plone.app.upgrade
Requires-Dist: Products.GenericSetup
Provides-Extra: test
Requires-Dist: plone.app.testing; extra == "test"
Requires-Dist: plone.app.dexterity; extra == "test"
Requires-Dist: plone.browserlayer; extra == "test"
Requires-Dist: pytest; extra == "test"
Requires-Dist: pytest-cov; extra == "test"
Requires-Dist: pytest-plone>=0.5.0; extra == "test"
Requires-Dist: plone.app.upgrade; extra == "test"
Provides-Extra: release
Requires-Dist: zest.releaser[recommended]; extra == "release"
Requires-Dist: zestreleaser.towncrier; extra == "release"
Requires-Dist: zest.pocompile; extra == "release"
Dynamic: author
Dynamic: author-email
Dynamic: classifier
Dynamic: description
Dynamic: description-content-type
Dynamic: home-page
Dynamic: keywords
Dynamic: license
Dynamic: license-file
Dynamic: project-url
Dynamic: provides-extra
Dynamic: requires-dist
Dynamic: requires-python
Dynamic: summary
